gamry_file_parser-0.1.0.dist-info/licenses/LICENSE
gamryparser/__init__.py
gamryparser/analysis.py
gamryparser/parsing.py
gamry_file_parser-0.1.0.dist-info/METADATA
gamry_file_parser-0.1.0.dist-info/WHEEL
gamry_file_parser-0.1.0.dist-info/top_level.txt
gamry_file_parser-0.1.0.dist-info/RECORD
