Metadata-Version: 2.4
Name: gamry-file-parser
Version: 0.1.0
Summary: A parser for Gamry EXPLAIN-formatted DTA files with neural interface specific data analysis
Author: Your Name
Author-email: Max Tenenbaum <maxtenenbaum223@gmail.com>
Project-URL: Homepage, https://github.com/maxtenenbaum/GamryParser
Project-URL: Issues, https://github.com/maxtenenbaum/GamryParser/issues
Classifier: Programming Language :: Python :: 3
Classifier: License :: OSI Approved :: MIT License
Classifier: Operating System :: OS Independent
Requires-Python: >=3.8
License-File: LICENSE
Requires-Dist: numpy
Requires-Dist: pandas
Dynamic: license-file
